tokmon/__init__.py
tokmon/beam.py
tokmon/cli.py
tokmon/costcalculator.py
tokmon/openai-pricing.json
tokmon/tokmon.py
tokmon/utils.py
tokmon-0.2.1.dist-info/LICENSE
tokmon-0.2.1.dist-info/METADATA
tokmon-0.2.1.dist-info/WHEEL
tokmon-0.2.1.dist-info/entry_points.txt
tokmon-0.2.1.dist-info/top_level.txt
tokmon-0.2.1.dist-info/RECORD
