Metadata-Version: 2.1
Name: tokmon
Version: 0.2.1
Summary: tokmon is a CLI utility to monitor OpenAI token usage and costs
Home-page: https://github.com/yagil/tokmon
Project-URL: Bug Reports, https://github.com/yagil/tokmon/issues
Project-URL: Source, https://github.com/yagil/tokmon/
License-File: LICENSE
Requires-Dist: mitmproxy
Requires-Dist: tiktoken
